Workbook

Sheet Resumen
A1: Santo Café — Validación pre-lanzamiento
A2: Marcá la columna 'Probado' (✔) en la hoja Checklist a medida que validás.
A4: Total casos | B4: =COUNTA(Checklist!A2:A224)
A5: Probados | B5: =COUNTIF(Checklist!H2:H224,"✔")
A6: Pendientes | B6: =B4-B5
A7: % Avance | B7: =IF(B4=0,0,B5/B4)
A8: OK | B8: =COUNTIF(Checklist!I2:I224,"OK")
A9: Fallas | B9: =COUNTIF(Checklist!I2:I224,"Falla")
A10: Bloqueantes sin probar | B10: =COUNTIFS(Checklist!J2:J224,"Bloqueante",Checklist!H2:H224,"")
A12: Por área
A13: Área | B13: Total | C13: Probados | D13: % Avance
A14: Global / Transversal | B14: =COUNTIF(Checklist!B2:B224,A14) | C14: =COUNTIFS(Checklist!B2:B224,A14,Checklist!H2:H224,"✔") | D14: =IF(B14=0,0,C14/B14)
A15: Home | B15: =COUNTIF(Checklist!B2:B224,A15) | C15: =COUNTIFS(Checklist!B2:B224,A15,Checklist!H2:H224,"✔") | D15: =IF(B15=0,0,C15/B15)
A16: Catálogo / Tienda | B16: =COUNTIF(Checklist!B2:B224,A16) | C16: =COUNTIFS(Checklist!B2:B224,A16,Checklist!H2:H224,"✔") | D16: =IF(B16=0,0,C16/B16)
A17: Ficha de producto | B17: =COUNTIF(Checklist!B2:B224,A17) | C17: =COUNTIFS(Checklist!B2:B224,A17,Checklist!H2:H224,"✔") | D17: =IF(B17=0,0,C17/B17)
A18: Carrito (drawer + página) | B18: =COUNTIF(Checklist!B2:B224,A18) | C18: =COUNTIFS(Checklist!B2:B224,A18,Checklist!H2:H224,"✔") | D18: =IF(B18=0,0,C18/B18)
A19: Checkout y Pago (Flow) | B19: =COUNTIF(Checklist!B2:B224,A19) | C19: =COUNTIFS(Checklist!B2:B224,A19,Checklist!H2:H224,"✔") | D19: =IF(B19=0,0,C19/B19)
A20: Post-compra | B20: =COUNTIF(Checklist!B2:B224,A20) | C20: =COUNTIFS(Checklist!B2:B224,A20,Checklist!H2:H224,"✔") | D20: =IF(B20=0,0,C20/B20)
A21: Mi cuenta | B21: =COUNTIF(Checklist!B2:B224,A21) | C21: =COUNTIFS(Checklist!B2:B224,A21,Checklist!H2:H224,"✔") | D21: =IF(B21=0,0,C21/B21)
A22: Emails | B22: =COUNTIF(Checklist!B2:B224,A22) | C22: =COUNTIFS(Checklist!B2:B224,A22,Checklist!H2:H224,"✔") | D22: =IF(B22=0,0,C22/B22)
A23: Guías / Contenido | B23: =COUNTIF(Checklist!B2:B224,A23) | C23: =COUNTIFS(Checklist!B2:B224,A23,Checklist!H2:H224,"✔") | D23: =IF(B23=0,0,C23/B23)
A24: Legales y Sistema | B24: =COUNTIF(Checklist!B2:B224,A24) | C24: =COUNTIFS(Checklist!B2:B224,A24,Checklist!H2:H224,"✔") | D24: =IF(B24=0,0,C24/B24)
A25: Casos borde y combinaciones | B25: =COUNTIF(Checklist!B2:B224,A25) | C25: =COUNTIFS(Checklist!B2:B224,A25,Checklist!H2:H224,"✔") | D25: =IF(B25=0,0,C25/B25)
A26: Performance / SEO / Seguridad / Deliverability | B26: =COUNTIF(Checklist!B2:B224,A26) | C26: =COUNTIFS(Checklist!B2:B224,A26,Checklist!H2:H224,"✔") | D26: =IF(B26=0,0,C26/B26)
A27: Pre-lanzamiento / Infra | B27: =COUNTIF(Checklist!B2:B224,A27) | C27: =COUNTIFS(Checklist!B2:B224,A27,Checklist!H2:H224,"✔") | D27: =IF(B27=0,0,C27/B27)
A28: TOTAL | B28: =SUM(B14:B27) | C28: =SUM(C14:C27) | D28: =IF(B28=0,0,C28/B28)

Sheet Checklist
A1: ID | B1: Área | C1: Pantalla/Panel | D1: Caso a validar | E1: Tipo | F1: Dispositivo | G1: Resultado esperado | H1: Probado | I1: Estado | J1: Severidad | K1: Navegador | L1: Notas
A2: GLOB-001 | B2: Global / Transversal | C2: Header/Navbar | D2: Logo visible y linkea a la home | E2: Diseño | F2: Desktop | G2: El logo aparece y lleva a la home | I2: Pendiente | J2: Media
A3: GLOB-002 | B3: Global / Transversal | C3: Header/Navbar | D3: Logo visible y linkea a la home | E3: Diseño | F3: Tablet | G3: El logo aparece y lleva a la home | I3: Pendiente | J3: Media
A4: GLOB-003 | B4: Global / Transversal | C4: Header/Navbar | D4: Logo visible y linkea a la home | E4: Diseño | F4: Mobile | G4: El logo aparece y lleva a la home | I4: Pendiente | J4: Media
A5: GLOB-004 | B5: Global / Transversal | C5: Header/Navbar | D5: Items de menú correctos, activos y con hover/focus | E5: Diseño | F5: Desktop | G5: Links correctos, estado activo y foco visibles | I5: Pendiente | J5: Media
A6: GLOB-005 | B6: Global / Transversal | C6: Header/Navbar | D6: Items de menú correctos, activos y con hover/focus | E6: Diseño | F6: Tablet | G6: Links correctos, estado activo y foco visibles | I6: Pendiente | J6: Media
A7: GLOB-006 | B7: Global / Transversal | C7: Header/Navbar | D7: Items de menú correctos, activos y con hover/focus | E7: Diseño | F7: Mobile | G7: Links correctos, estado activo y foco visibles | I7: Pendiente | J7: Media
A8: GLOB-007 | B8: Global / Transversal | C8: Header/Navbar | D8: Ícono de cuenta cambia según logueado / no logueado | E8: Funcional | F8: — | G8: Muestra el estado correcto y abre cuenta/login | I8: Pendiente | J8: Media
A9: GLOB-008 | B9: Global / Transversal | C9: Header/Navbar | D9: Badge del carrito con cantidad correcta y estado vacío | E9: Funcional | F9: — | G9: El número coincide con el carrito; vacío sin badge | I9: Pendiente | J9: Alta
A10: GLOB-009 | B10: Global / Transversal | C10: Header/Navbar | D10: Padding del header se mantiene con y sin banner de envío | E10: Diseño | F10: Desktop | G10: El alto/padding no cambia al mostrar la línea amarilla | I10: Pendiente | J10: Media
A11: GLOB-010 | B11: Global / Transversal | C11: Header/Navbar | D11: Padding del header se mantiene con y sin banner de envío | E11: Diseño | F11: Tablet | G11: El alto/padding no cambia al mostrar la línea amarilla | I11: Pendiente | J11: Media
A12: GLOB-011 | B12: Global / Transversal | C12: Header/Navbar | D12: Padding del header se mantiene con y sin banner de envío | E12: Diseño | F12: Mobile | G12: El alto/padding no cambia al mostrar la línea amarilla | I12: Pendiente | J12: Media
A13: GLOB-012 | B13: Global / Transversal | C13: Header/Navbar | D13: Navbar transparente sobre hero y sólido al scrollear | E13: Diseño | F13: Desktop | G13: Transición correcta al hacer scroll | I13: Pendiente | J13: Baja
... A224: INFRA-011 | B224: Pre-lanzamiento / Infra | C224: Infra | D224: Sacar 'Disuadir motores de búsqueda' al salir a producción | E224: Integración | F224: — | G224: El sitio queda indexable | I224: Pendiente | J224: Alta

Sheet Leyenda
A1: Cómo usar
A2: Probado | B2: Elegí ✔ del desplegable cuando el caso quedó validado (la celda se pone verde).
A3: Estado | B3: Pendiente / OK / Falla / N/A / Bloqueado (OK=verde, Falla=rojo).
A4: Severidad | B4: Bloqueante / Alta / Media / Baja. Bloqueante/Alta resaltadas.
A5: Dispositivo | B5: Los casos de diseño están separados en Desktop, Tablet y Mobile.
A6: Filtros | B6: La hoja Checklist tiene filtros: filtrá por Área, Tipo, Estado, Severidad, etc.
A7: Resumen | B7: Se calcula solo (avance %, fallas, bloqueantes sin probar) a partir del Checklist.
A9: Tipos
A10: Funcional | B10: Comportamiento / que la acción haga lo que debe.
A11: Contenido | B11: Textos, datos, precios, ortografía, tuteo.
A12: Diseño | B12: Layout y responsive (revisar en D/T/M).
A13: Borde | B13: Casos límite, errores y combinaciones.
A14: Integración | B14: Emails, pagos, analytics, terceros, infra.
